chat_research/__init__.py
chat_research/__main__.py
chat_research/aexport.py
chat_research/areader.py
chat_research/commands/chat_async_arxiv.py
chat_research/commands/chat_async_biorxiv.py
chat_research/commands/chat_async_paper.py
chat_research/commands/chat_config.py
chat_research/commands/chat_response.py
chat_research/commands/chat_reviewer.py
chat_research/export.py
chat_research/paper.py
chat_research/paper_with_image.py
chat_research/provider/arxiv.py
chat_research/provider/async_arxiv.py
chat_research/provider/async_biorxiv.py
chat_research/summary.py
chat_research/template/__init__.py
chat_research/template/eisvogel.tex
chat_research/utils.py
chat_research-0.1.13.dist-info/LICENSE
chat_research-0.1.13.dist-info/METADATA
chat_research-0.1.13.dist-info/WHEEL
chat_research-0.1.13.dist-info/entry_points.txt
chat_research-0.1.13.dist-info/RECORD
