Metadata-Version: 2.1
Name: chat-research
Version: 0.1.13
Summary: Use ChatGPT to accelerator your research.
Home-page: https://github.com/cauliyang/ChatResearch
License: MIT
Author: Yangyang Li
Author-email: yangyang.li@northwestern.edu
Requires-Python: >=3.9,<4.0
Classifier: Development Status :: 2 - Pre-Alpha
Classifier: Environment :: Console
Classifier: License :: OSI Approved :: MIT License
Classifier: Programming Language :: Python :: 3
Classifier: Programming Language :: Python :: 3.9
Classifier: Programming Language :: Python :: 3.10
Classifier: Programming Language :: Python :: 3.11
Classifier: Programming Language :: Python :: 3.10
Classifier: Programming Language :: Python :: 3.9
Requires-Dist: aiohttp[speedups] (>=3.8.4,<4.0.0)
Requires-Dist: arxiv (>=1.4.3,<2.0.0)
Requires-Dist: bs4 (>=0.0.1,<0.0.2)
Requires-Dist: fake-useragent (>=1.1.3,<2.0.0)
Requires-Dist: loguru (>=0.6,<0.8)
Requires-Dist: markdown (>=3.4.3,<4.0.0)
Requires-Dist: openai (>=0.27.2,<0.28.0)
Requires-Dist: pillow (>=9.5.0,<10.0.0)
Requires-Dist: pybase64 (>=1.2.3,<2.0.0)
Requires-Dist: pydantic (>=1.10.7,<2.0.0)
Requires-Dist: pymupdf (>=1.21.1,<2.0.0)
Requires-Dist: requests (>=2.28.2,<3.0.0)
Requires-Dist: rich (>=13.3.3,<14.0.0)
Requires-Dist: tenacity (>=8.2.2,<9.0.0)
Requires-Dist: tiktoken (>=0.3.3,<0.4.0)
Requires-Dist: toml (>=0.10.2,<0.11.0)
Requires-Dist: types-requests (>=2.28.11.17,<3.0.0.0)
Project-URL: Documentation, https://github.com/cauliyang/ChatResearch
Project-URL: Repository, https://github.com/cauliyang/ChatResearch
